setup.py
baibaoxiang/__init__.py
baibaoxiang/baibaoxiang.py
baibaoxiang/baibaoxiangInterface.py
baibaoxiang/baibaoxiangMobile.py
baibaoxiang/excel.py
baibaoxiang/excel_xlwt.py
baibaoxiang/femail.py
baibaoxiang/image.py
baibaoxiang/sql.py
baibaoxiang/sys_powel.py
baibaoxiang/xingneng.py
chenyabaibaoxiang.egg-info/PKG-INFO
chenyabaibaoxiang.egg-info/SOURCES.txt
chenyabaibaoxiang.egg-info/dependency_links.txt
chenyabaibaoxiang.egg-info/top_level.txt