Metadata-Version: 1.0
Name: chenyabaibaoxiang
Version: 3.5.1
Summary: this is novice help
Home-page: https://www.baidu.com
Author: dashu
Author-email: bj_xiaoya@163.com
License: test Licence
Keywords: dashu,baibaoxiang
Platform: any
